<annotation>
	<folder>mcindoor</folder>
	<filename>MNT_006.jpg</filename>
	<source>
		<database>Sata_data_extension</database>
		<annotation>PascalVOC</annotation>
		<image>flickr</image>
		<flickrid>NULL</flickrid>
	</source>
	<owner>
		<flickrid>NULL</flickrid>
		<name>Wenbo</name>
	</owner>
	<size>
		<width>1280</width>
		<height>720</height>
		<depth>3</depth>
	</size>
	<segmented>1</segmented>
	<object>
		<name>person</name>
		<pose>Unspecified</pose>
		<truncated>1</truncated>
		<difficult>0</difficult>
		<bndbox>
			<xmin>2.487562189054726</xmin>
			<ymin>24.87562189054726</ymin>
			<xmax>266.66666666666663</xmax>
			<ymax>394.52736318407955</ymax>
		</bndbox>
	</object>
	<object>
		<name>person</name>
		<pose>Unspecified</pose>
		<truncated>1</truncated>
		<difficult>0</difficult>
		<bndbox>
			<xmin>312.93532338308455</xmin>
			<ymin>140.7960199004975</ymin>
			<xmax>385.0746268656716</xmax>
			<ymax>297.51243781094524</ymax>
		</bndbox>
	</object>
	<object>
		<name>person</name>
		<pose>Unspecified</pose>
		<truncated>1</truncated>
		<difficult>0</difficult>
		<bndbox>
			<xmin>581.5920398009949</xmin>
			<ymin>220.89552238805967</ymin>
			<xmax>729.8507462686566</xmax>
			<ymax>383.0845771144278</ymax>
		</bndbox>
	</object>
	<object>
		<name>tvmonitor</name>
		<pose>Unspecified</pose>
		<truncated>1</truncated>
		<difficult>0</difficult>
		<bndbox>
			<xmin>514.4278606965173</xmin>
			<ymin>167.1641791044776</ymin>
			<xmax>585.5721393034826</xmax>
			<ymax>222.38805970149252</ymax>
		</bndbox>
	</object>
	<object>
		<name>tvmonitor</name>
		<pose>Unspecified</pose>
		<truncated>1</truncated>
		<difficult>0</difficult>
		<bndbox>
			<xmin>703.4825870646765</xmin>
			<ymin>205.9701492537313</ymin>
			<xmax>766.1691542288556</xmax>
			<ymax>241.79104477611938</ymax>
		</bndbox>
	</object>
</annotation>