<annotation>
	<folder>mcindoor</folder>
	<filename>new_scr_06.jpg</filename>
	<source>
		<database>MCIndoor20000</database>
		<annotation>PascalVOC</annotation>
		<image>flickr</image>
		<flickrid>NULL</flickrid>
	</source>
	<owner>
		<flickrid>NULL</flickrid>
		<name>Wenbo</name>
	</owner>
	<size>
		<width>1440</width>
		<height>1080</height>
		<depth>3</depth>
	</size>
	<segmented>1</segmented>
	<object>
		<name>sign</name>
		<pose>Unspecified</pose>
		<truncated>1</truncated>
		<difficult>0</difficult>
		<bndbox>
			<xmin>699</xmin>
			<ymin>249</ymin>
			<xmax>987</xmax>
			<ymax>358</ymax>
		</bndbox>
	</object>
	<object>
		<name>sign</name>
		<pose>Unspecified</pose>
		<truncated>1</truncated>
		<difficult>0</difficult>
		<bndbox>
			<xmin>772</xmin>
			<ymin>405</ymin>
			<xmax>878</xmax>
			<ymax>505</ymax>
		</bndbox>
	</object>
	<object>
		<name>tvmonitor</name>
		<pose>Unspecified</pose>
		<truncated>1</truncated>
		<difficult>0</difficult>
		<bndbox>
			<xmin>798</xmin>
			<ymin>669</ymin>
			<xmax>967</xmax>
			<ymax>889</ymax>
		</bndbox>
	</object>
	<object>
		<name>tvmonitor</name>
		<pose>Unspecified</pose>
		<truncated>1</truncated>
		<difficult>0</difficult>
		<bndbox>
			<xmin>165</xmin>
			<ymin>631</ymin>
			<xmax>335</xmax>
			<ymax>821</ymax>
		</bndbox>
	</object>
</annotation>