<annotation>
	<folder>mcindoor</folder>
	<filename>STR_S1_13.jpg</filename>
	<source>
		<database>MCIndoor20000</database>
		<annotation>PascalVOC</annotation>
		<image>flickr</image>
		<flickrid>NULL</flickrid>
	</source>
	<owner>
		<flickrid>NULL</flickrid>
		<name>Wenbo</name>
	</owner>
	<size>
		<width>3615</width>
		<height>2712</height>
		<depth>3</depth>
	</size>
	<segmented>1</segmented>
	<object>
		<name>stair</name>
		<pose>Unspecified</pose>
		<truncated>1</truncated>
		<difficult>0</difficult>
		<bndbox>
			<xmin>0</xmin>
			<ymin>12</ymin>
			<xmax>1739</xmax>
			<ymax>1582</ymax>
		</bndbox>
	</object>
	<object>
		<name>stair</name>
		<pose>Unspecified</pose>
		<truncated>1</truncated>
		<difficult>0</difficult>
		<bndbox>
			<xmin>1704</xmin>
			<ymin>1658</ymin>
			<xmax>3614</xmax>
			<ymax>1869</ymax>
		</bndbox>
	</object>
</annotation>